Workbook

Sheet Assumptions
A1: Cheerio AI — Co-Pilot Financial & Unit Economics Model: Assumptions
A2: Single Source of Truth • Candidate: Saksham Gupta (saksham77779@gmail.com)
A4: Parameter Code | B4: Parameter Description | C4: Value | D4: Unit | E4: Type | F4: Source URL / Benchmark Rationale | G4: Access / Verification Date
A5: BIZ_BASE | B5: Active Merchant Customer Base | C5: 5000 | D5: Businesses | E5: Given in Brief | F5: Cheerio Assignment Brief specification | G5: Oct 2026
A6: QUERY_RATE | B6: Monthly Support Query Rate per Merchant | C6: 3.5 | D6: Queries / biz / mo | E6: Stated Assumption | F6: 5-7 queries in Month 1 onboarding; 1-2 in mature phase | G6: Oct 2026
A7: FX_USD_INR | B7: USD to INR Exchange Rate | C7: 84 | D7: INR / USD | E7: Industry Benchmark | F7: RBI Reference Exchange Rate (rbi.org.in) | G7: Oct 2026
A8: LLM_IN_PRICE | B8: GPT-4o-mini Input Token Price | C8: 0.15 | D8: USD / 1M tokens | E8: Verified API Pricing | F8: https://openai.com/api/pricing | G8: Oct 2026
A9: LLM_IN_CACHE | B9: GPT-4o-mini Cached Input Token Price | C9: 0.075 | D9: USD / 1M tokens | E9: Verified API Pricing | F9: https://openai.com/api/pricing (50% cache hit discount) | G9: Oct 2026
A10: LLM_OUT_PRICE | B10: GPT-4o-mini Output Token Price | C10: 0.6 | D10: USD / 1M tokens | E10: Verified API Pricing | F10: https://openai.com/api/pricing | G10: Oct 2026
A11: TOKENS_IN | B11: Average Input Tokens per Query Session | C11: 2500 | D11: Tokens / query | E11: Stated Assumption | F11: System prompt (1k) + error payload (500) + 3 turns (1k) | G11: Oct 2026
A12: TOKENS_OUT | B12: Average Output Tokens per Query Session | C12: 500 | D12: Tokens / query | E12: Stated Assumption | F12: Structured diagnostic + JSON remediation payload | G12: Oct 2026
A13: INFRA_OVERHEAD | B13: Serverless & Redis Cache Buffer | C13: 0.1433 | D13: INR / query | E13: Industry Benchmark | F13: Cloudflare Workers & Upstash Redis semantic cache | G13: Oct 2026
A14: AGENT_SALARY | B14: Human Support Rep Monthly Salary | C14: 35000 | D14: INR / agent / mo | E14: Industry Benchmark | F14: Glassdoor / AmbitionBox Indian B2B SaaS CS benchmark | G14: Oct 2026
A15: WORK_DAYS | B15: Working Days per Month | C15: 22 | D15: Days / mo | E15: Standard Work Week | F15: 5-day work week standard | G15: Oct 2026
A16: AGENT_TICKETS_DAY | B16: Daily Ticket Handling Capacity per Rep | C16: 40 | D16: Tickets / agent / day | E16: Stated Assumption | F16: Assumes 12 mins per ticket across async chat / email | G16: Oct 2026
... A26: META_MKT_RATE | B26: Meta India Marketing Message Delivery Rate | C26: 0.8631 | D26: INR / msg | E26: Verified Meta Doc | F26: https://developers.facebook.com/docs/whatsapp/pricing | G26: Oct 2026

Sheet Executive_Summary
A1: Cheerio AI — Customer Support Scaling Executive Summary
A2: Financial Model & Unit Economics Summary • Evaluated at 5,000 Active Merchants
A4: Key Operational Metric | B4: Baseline (Human Only) | C4: With Cheerio Co-Pilot | D4: Delta / Impact | E4: Source & Formula Reference
A5: Active Merchant Base | B5: =Assumptions!C5 | C5: =Assumptions!C5 | D5: 0 (Baseline) | E5: Assumptions!C5
A6: Total Monthly Inbound Queries | B6: =Volume_Model!B7 | C6: =Volume_Model!B7 | D6: 0 (Baseline) | E6: Volume_Model!B7 (17,500 queries)
A7: Autonomous Ticket Deflection Rate | B7: =Assumptions!C17 | C7: =Assumptions!C18 | D7: +53.0% | E7: Assumptions!C17 vs C18
A8: Human Support Headcount Required | B8: =Human_Comparison!B10 | C8: =Human_Comparison!B16 | D8: -13 Agents Avoided | E8: Human_Comparison!B10 vs B16
A9: Total Monthly Support Running Cost (₹) | B9: =Human_Comparison!B11 | C9: =Human_Comparison!B21 | D9: -₹4,36,500 / mo | E9: Human_Comparison!B11 vs B21
A10: Cost per Resolved Ticket (₹) | B10: =Human_Comparison!B12 | C10: =Human_Comparison!B22 | D10: -₹24.94 / ticket (-62.4%) | E10: Human_Comparison!B12 vs B22
A11: Monthly AI Token & Infra Cost (₹) | B11: 0 | C11: =Token_Economics!B18 | D11: +₹3,500 / mo | E11: Token_Economics!B18 (17,500 queries @ ₹0.20)
A12: Monthly Observability & Tooling (₹) | B12: 0 | C12: =Assumptions!C21 | D12: +₹15,000 / mo | E12: Assumptions!C21 (LangSmith / Datadog)
A13: Net Monthly Operational Cost Savings (₹) | B13: 0 | C13: =Human_Comparison!B25 | D13: +₹4,36,500 / mo | E13: Human_Comparison!B25 (₹52.38L / yr)
A14: One-Time Development Build Cost (₹) | B14: 0 | C14: =Assumptions!C20 | D14: ₹2,50,000 | E14: Assumptions!C20 (1 Eng for 1 Month)
A15: CapEx Payback Period (Months) | B15: - | C15: =ROUND(Assumptions!C20/Human_Comparison!B25, 2) | D15: 0.57 Months (~17 Days) | E15: Build Cost / Net Monthly Savings
A16: Gross Merchant Retention ROI | B16: - | C16: =Retention_ROI!B16 | D16: 51.4x Return | E16: Retention_ROI!B16 (Gross MRR / AI Spend)
A17: Net Merchant Retention ROI | B17: - | C17: =Retention_ROI!B17 | D17: 50.4x Return | E17: Retention_ROI!B17 (Net MRR / AI Spend)

Sheet Volume_Model
A1: Support Volume & Resolution Breakdown
A2: 5,000 Active Businesses Model • All inputs dynamically linked to Assumptions tab
A4: Parameter | B4: Value | C4: Unit | D4: Notes & Operational Logic
A5: Active Business Accounts | B5: =Assumptions!C5 | C5: Businesses | D5: Assumptions!C5 (Given active merchant count)
A6: Monthly Support Query Rate per Business | B6: =Assumptions!C6 | C6: Queries / mo | D6: Assumptions!C6 (Blended across onboarding & mature accounts)
A7: Total Monthly Inbound Queries | B7: =B5*B6 | C7: Queries / mo | D7: 17,500 total queries across all support channels
A8: Current Baseline Deflection Rate | B8: =Assumptions!C17 | C8: % deflected | D8: Assumptions!C17 (Status quo static FAQ deflection)
A9: Cheerio Co-Pilot Target Deflection Rate (Base) | B9: =Assumptions!C18 | C9: % deflected | D9: Assumptions!C18 (65% target across top 5 bottlenecks)
A10: Queries Resolved Autonomously by AI | B10: =ROUND(B7*B9, 0) | C10: Queries / mo | D10: =17,500 * 65% = 11,375 queries without human rep
A11: Queries Escalated to Human Support | B11: =B7-B10 | C11: Queries / mo | D11: =17,500 - 11,375 = 6,125 escalated queries

Sheet Token_Economics
A1: AI Token Economics, Pricing & Stress-Test Sensitivity
A2: Source: OpenAI API Pricing (GPT-4o-mini), USD:INR = 84.0
A4: Token Cost Parameter | B4: Value | C4: Unit | D4: Source URL & Benchmarking Logic
A5: Model Chosen | B5: GPT-4o-mini | C5: LLM | D5: Multi-tier hybrid: Regex linter + GPT-4o-mini rephraser
A6: USD to INR Exchange Rate | B6: =Assumptions!C7 | C6: INR / USD | D6: Assumptions!C7 (RBI reference rate)
A7: Input Token Price per 1M Tokens ($) | B7: =Assumptions!C8 | C7: USD / 1M | D7: Assumptions!C8 (openai.com/api/pricing)
A8: Output Token Price per 1M Tokens ($) | B8: =Assumptions!C10 | C8: USD / 1M | D8: Assumptions!C10 (openai.com/api/pricing)
A9: Average Input Tokens per Session | B9: =Assumptions!C11 | C9: Tokens | D9: Assumptions!C11 (Prompt 1k + error 500 + 3 turns 1k)
A10: Average Output Tokens per Session | B10: =Assumptions!C12 | C10: Tokens | D10: Assumptions!C12 (Remediation payload)
A11: Input Cost per Query Session ($) | B11: =(B9/1000000)*B7 | C11: USD | D11: =(Tokens / 1M) * Input Rate
A12: Output Cost per Query Session ($) | B12: =(B10/1000000)*B8 | C12: USD | D12: =(Tokens / 1M) * Output Rate
A13: Total LLM Cost per Query Session ($) | B13: =B11+B12 | C13: USD | D13: =Input Cost + Output Cost
A14: Total LLM Cost per Query Session (₹) | B14: =B13*B6 | C14: INR | D14: Converted to INR (approx 5.67 paise)
A15: Serverless & Redis Cache Overhead (₹) | B15: =Assumptions!C13 | C15: INR | D15: Assumptions!C13 (Edge worker execution + Redis cache)
A16: Total Operational Cost per Query (₹) | B16: =B14+B15 | C16: INR | D16: Blended total cost per query touched by AI (₹0.20)
A17: Total Monthly Queries Touched by AI | B17: =Volume_Model!B7 | C17: Queries / mo | D17: Volume_Model!B7 (AI touches all 17,500 inbound queries)
A18: Total Monthly AI Token & Infra Cost (₹) | B18: =ROUND(B16*B17, 0) | C18: INR / mo | D18: =17,500 queries * ₹0.20 = ₹3,500 / month
A19: AI Cost per Active Business / Month (₹) | B19: =ROUND(B18/Volume_Model!B5, 2) | C19: INR / biz / mo | D19: =₹3,500 / 5,000 = ₹0.70 / merchant / month
A22: SENSITIVITY MATRIX: Monthly AI Cost (₹) Under Token Volume & API Price Surges
A23: Token Volume Multiple | B23: 1x Price ($0.15/$0.60) | C23: 3x Price ($0.45/$1.80) | D23: 5x Price ($0.75/$3.00)
A24: 1x Tokens (3,000 tokens/session) | B24: =ROUND(17500*(B14*1 + B15), 0) | C24: =ROUND(17500*(B14*3 + B15), 0) | D24: =ROUND(17500*(B14*5 + B15), 0)
A25: 2x Tokens (6,000 tokens/session) | B25: =ROUND(17500*(B14*2 + B15), 0) | C25: =ROUND(17500*(B14*6 + B15), 0) | D25: =ROUND(17500*(B14*10 + B15), 0)
A26: 3x Tokens (9,000 tokens/session) | B26: =ROUND(17500*(B14*3 + B15), 0) | C26: =ROUND(17500*(B14*9 + B15), 0) | D26: =ROUND(17500*(B14*15 + B15), 0)

Sheet Human_Comparison
A1: Support Scaling: Avoided Support Hiring & Operating Cost Analysis
A2: Framed as Avoided Headcount as Cheerio Scales • Agent Capacity: 40 tickets/day @ ₹35k/mo
A4: Cost & Staffing Parameter | B4: Value | C4: Unit | D4: Operational Formula & Rationale
A5: Human Support Rep Monthly Salary (₹) | B5: =Assumptions!C14 | C5: INR / agent / mo | D5: Assumptions!C14 (Glassdoor/AmbitionBox CS rep benchmark)
A6: Working Days per Month | B6: =Assumptions!C15 | C6: Days | D6: Assumptions!C15 (Standard 5-day work week)
A7: Daily Ticket Capacity per Agent | B7: =Assumptions!C16 | C7: Tickets / day | D7: Assumptions!C16 (Standard chat/ticket handling capacity)
A8: Monthly Ticket Capacity per Agent | B8: =B5*B6 | C8: Tickets / mo | D8: =22 days * 40 tickets/day = 880 tickets / rep / mo
A9: --- MODEL 1: PURE HUMAN SUPPORT (AVOIDED BASELINE) ---
A10: Total Inbound Query Volume | B10: =Volume_Model!B7 | C10: Tickets / mo | D10: 17,500 total queries
A11: Human Support Agents Needed (Without AI) | B11: =ROUNDUP(B10/B8, 0) | C11: Agents | D11: =ROUNDUP(17,500 / 880) = 20 Agents needed to maintain SLA
A12: Total Monthly Human Support Cost (₹) | B12: =B11*B5 | C12: INR / mo | D12: =20 agents * ₹35,000/mo = ₹7,00,000 / month
A13: Cost per Resolved Ticket (Pure Human) (₹) | B13: =ROUND(B12/B10, 2) | C13: INR / ticket | D13: =₹7,00,000 / 17,500 = ₹40.00 / ticket
A14: --- MODEL 2: CHEERIO CO-PILOT + SCALED HUMAN ESCALATION ---
A15: Queries Handled Autonomously by Co-Pilot (65%) | B15: =Volume_Model!B10 | C15: Tickets / mo | D15: 11,375 tickets resolved without human intervention
A16: Queries Escalated to Human Support (35%) | B16: =Volume_Model!B11 | C16: Tickets / mo | D16: 6,125 tickets requiring human specialist review
A17: Human Agents Needed for Escalations | B17: =ROUNDUP(B16/B8, 0) | C17: Agents | D17: =ROUNDUP(6,125 / 880) = 7 Agents required
A18: Scaled Human Support Salary Cost (₹) | B18: =B17*B5 | C18: INR / mo | D18: =7 agents * ₹35,000/mo = ₹2,45,000 / month
A19: Monthly AI Token & Infra Cost (₹) | B19: =Token_Economics!B18 | C19: INR / mo | D19: Token_Economics!B18 (₹3,500 LLM token cost)
A20: Monthly Observability Tooling (₹) | B20: =Assumptions!C21 | C20: INR / mo | D20: Assumptions!C21 (LangSmith / Datadog APM = ₹15,000)
A21: Total Monthly Blended Support Running Cost (₹) | B21: =B18+B19+B20 | C21: INR / mo | D21: =₹2,45,000 salary + ₹3,500 AI + ₹15,000 tooling = ₹2,63,500
A22: Blended Cost per Ticket (₹) | B22: =ROUND(B21/B10, 2) | C22: INR / ticket | D22: =₹2,63,500 / 17,500 = ₹15.06 / ticket
A23: --- NET OPERATIONAL SAVINGS & PAYBACK ---
A24: Avoided Headcount (Agents) | B24: =B11-B17 | C24: Agents | D24: =20 agents - 7 agents = 13 agents avoided
A25: Net Monthly Operational Savings (₹) | B25: =B12-B21 | C25: INR / mo | D25: =₹7,00,000 - ₹2,63,500 = ₹4,36,500 / month
A26: Net Annual Operational Savings (₹) | B26: =B25*12 | C26: INR / yr | D26: =₹4,36,500 * 12 = ₹52.38 Lakhs / year
A27: One-Time Development Build Cost (₹) | B27: =Assumptions!C20 | C27: INR | D27: Assumptions!C20 (₹2,50,000 dev build cost)
A28: Payback Period on Build Investment | B28: =ROUND(B27/B25, 2) | C28: Months | D28: =₹2,50,000 / ₹4,36,500 = 0.57 Months (~17 Days)
A31: DEFLECTION SCENARIO ANALYSIS (Impact on Agents Needed & Net Savings)
A32: Scenario | B32: Deflection Rate | C32: Escalated Queries | D32: Agents Needed | E32: Blended Support Cost (₹) | F32: Net Monthly Savings (₹)
A33: Conservative (Low) | B33: 0.45 | C33: =ROUND(17500*(1-B33),0) | D33: =ROUNDUP(C33/880,0) | E33: =(D33*35000)+18500 | F33: =700000-E33
A34: Expected (Base) | B34: 0.65 | C34: =ROUND(17500*(1-B34),0) | D34: =ROUNDUP(C34/880,0) | E34: =(D34*35000)+18500 | F34: =700000-E34
A35: Aggressive (High) | B35: 0.75 | C35: =ROUND(17500*(1-B35),0) | D35: =ROUNDUP(C35/880,0) | E35: =(D35*35000)+18500 | F35: =700000-E35

Sheet Retention_ROI
A1: Merchant Retention & Churn Reduction Economics
A2: Separated from Support Headcount Savings • No Double Counting
A4: Retention & Revenue Parameter | B4: Value | C4: Unit | D4: Strategic Rationale & Verification Formula
A5: Active Merchant Base | B5: =Assumptions!C5 | C5: Businesses | D5: Assumptions!C5 (Given customer base)
A6: Estimated Average Monthly Subscription (ARPU) | B6: =Assumptions!C22 | C6: INR / biz / mo | D6: Assumptions!C22 (₹2,999 / month standard tier)
A7: Total Baseline Monthly Recurring Revenue (MRR) | B7: =B5*B6 | C7: INR / mo | D7: =5,000 * ₹2,999 = ₹1,49,95,000 / month (~₹1.50 Cr)
A8: Baseline Monthly Merchant Churn Rate | B8: =Assumptions!C23 | C8: % / mo | D8: Assumptions!C23 (5.0% monthly SMB churn benchmark)
A9: Lost Businesses per Month (Baseline Churn) | B9: =ROUND(B5*B8, 0) | C9: Businesses / mo | D9: =5,000 * 5% = 250 merchants lost each month
A10: Estimated Churn Reduction via Co-Pilot (Base) | B10: =Assumptions!C24 | C10: % absolute | D10: Assumptions!C24 (1.2% saved by fixing onboarding drop-offs)
A11: Preserved Businesses per Month | B11: =ROUND(B5*B10, 0) | C11: Businesses / mo | D11: =5,000 * 1.2% = 60 merchants retained every month
A12: Gross Preserved Monthly Recurring Revenue (MRR) | B12: =B11*B6 | C12: INR / mo | D12: =60 merchants * ₹2,999 = ₹1,79,940 / month
A13: Gross Preserved Annual Recurring Revenue (ARR) | B13: =B12*12 | C13: INR / yr | D13: =₹1,79,940 * 12 = ₹21.59 Lakhs / year
A14: Monthly Cheerio Co-Pilot AI Token Cost (₹) | B14: =Token_Economics!B18 | C14: INR / mo | D14: Token_Economics!B18 (₹3,500 total monthly AI spend)
A15: Net Monthly Retained Financial Value (₹) | B15: =B12-B14 | C15: INR / mo | D15: =Gross Preserved MRR - AI Spend = ₹1,76,440 / month
A16: Gross ROI on AI Spend | B16: =ROUND(B12/B14, 1) | C16: x Return | D16: =Gross Preserved MRR / AI Spend = ₹1,79,940 / ₹3,500 = 51.4x
A17: Net ROI on AI Spend | B17: =ROUND(B15/B14, 1) | C17: x Return | D17: =Net Retained MRR / AI Spend = ₹1,76,440 / ₹3,500 = 50.4x
A20: CHURN REDUCTION SENSITIVITY TABLE (Low / Base / High)
A21: Scenario | B21: Absolute Churn Reduction | C21: Retained Merchants/Mo | D21: Gross Preserved MRR (₹) | E21: Net Preserved MRR (₹) | F21: Net ROI Multiple
A22: Conservative (Low) | B22: 0.005 | C22: =ROUND(5000*B22,0) | D22: =C22*2999 | E22: =D22-3500 | F22: =ROUND(E22/3500,1)
A23: Expected (Base) | B23: 0.012 | C23: =ROUND(5000*B23,0) | D23: =C23*2999 | E23: =D23-3500 | F23: =ROUND(E23/3500,1)
A24: Aggressive (High) | B24: 0.02 | C24: =ROUND(5000*B24,0) | D24: =C24*2999 | E24: =D24-3500 | F24: =ROUND(E24/3500,1)

Sheet Billing_Strategy
A1: Packaging, Monetization & Billing Strategy Options
A2: Evaluates 4 Pricing Models with Fully Loaded Unit Costs & Margins
A4: Pricing Model | B4: Customer Price | C4: Billing Basis | D4: Fully Loaded Unit Cost (₹) | E4: Gross Margin (%) | F4: Strategic Fit & Recommendation
A5: Model 1: 100% Free Core Feature (Recommended) | B5: 0 | C5: Free for all active merchants | D5: 6.26 | E5: Subsidized | F5: Maximizes onboarding completion & retention. Subsidized by 50.4x Retention ROI.
A6: Model 2: Per-Resolution Micro-Fee | B6: 5 | C6: Per resolved troubleshooting workflow | D6: 0.3 | E6: =ROUND((B6-D6)/B6, 3) | F6: Friction for SMBs; disincentivizes self-service and causes support backlash.
A7: Model 3: Prepaid AI Credits Pack | B7: 199 | C7: Pack of 50 AI resolutions (₹3.98/res) | D7: 15 | E7: =ROUND((B7-D7)/B7, 3) | F7: High margin (+92.5%), but adds onboarding barrier during crucial activation.
A8: Model 4: Premium Dedicated Support Add-On | B8: 499 | C8: Per business / month (Unlimited AI + Priority) | D8: 22.5 | E8: =ROUND((B8-D8)/B8, 3) | F8: Viable for high-volume enterprise senders; 95.5% margin, optional add-on.
A11: FULLY LOADED COST PER RESOLUTION BREAKDOWN (₹)
A12: LLM Token Inference (GPT-4o-mini blended) | B12: 0.2 | C12: Token_Economics!B16
A13: Observability & Cache Overhead (LangSmith + Redis) | B13: 0.1 | C13: Allocated tooling buffer
A14: Amortized Human Escalation Share (across 35% unassisted queries) | B14: 5.96 | C14: =Human_Comparison!B18 / Volume_Model!B7
A15: Total Fully Loaded Cost per Support Query (₹) | B15: =B12+B13+B14 | C15: Complete blended operational cost per interaction

Sheet Audit_Governance
A1: Co-Pilot Observability, Governance & Monthly Audit Protocol
A2: Alert Thresholds, Operational Cadence & Assigned Owners
A4: Audit Parameter / Check | B4: Threshold / Benchmark | C4: Severity | D4: Assigned Owner | E4: Automated Action / Remediation Protocol
A5: Cost per Resolved Query | B5: > 2x Baseline (> ₹0.40 / query) | C5: High | D5: Lead APM / ML Eng | E5: Flag prompt regression or runaway token loops; fallback to strict regex
A6: Average Tokens per Session | B6: > 140% 7-day rolling avg (> 4,200 tokens) | C6: Medium | D6: Backend Lead | E6: Audit error payload serialization and trim oversized CSV schema payloads
A7: Single-Merchant Session Spikes | B7: > 50 sessions / 24 hours | C7: High | D7: SecOps / CS Lead | E7: Throttle merchant rate limit; trigger white-glove onboarding call
A8: Zero-Touch Deflection Rate (ZOCR) | B8: < 40% (Target: 65%) | C8: Critical | D8: Product Manager | E8: Review Meta Cloud API error changes; retrain diagnostic intent embeddings
A9: 7-Day Ticket Reopen Rate | B9: > 5.0% of deflected tickets | C9: High | D9: QA Lead / Support Lead | E9: Audit auto-fix false positives; refine pre-flight regex linter rules
A10: Monthly Token Invoice Reconciliation | B10: OpenAI invoice vs logs variance > ±2% | C10: Medium | D10: Finance / Eng Lead | E10: Reconcile dropped webhooks, orphaned sessions, or billing discrepancies
